{
    "nombre":"Turismo Costa Rica",
    "btnNavInicio":"Inicio",
    "btnNavAcercaDe":"Acerca de",
    "btnNavTurismos":"Turismos",
    "btnNavCotizarServicio":"Cotizar servicio",
    "btnNavContactos":"Contactos",
    "btnNavIdioma":"Idioma",
    "es":"Español",
    "en":"Ingles",
    "titulo": "Solución creativa e innovadora",
    "subtitulo": "CREATIVOS E INNOVADORES",
    "btn1Corousel":"Cotización Gratis",
    "btn1Corouse2":"Contactenos",
    "btn1CorouseAnt":"Anterior",
    "btn1CorouseSigu":"Siguiente",
    "Facts": [
        {
          "titulo": "Clientes Satisfechos",
          "total": "1000",
          "colorFond": "bg-success shadow d-flex align-items-center justify-content-center p-4",
          "colorIcon": "fa fa-users text-success"
        },
        {
          "titulo": "Servicios que ofrecemos",
          "total": "5",
          "colorFond": "bg-secondary bg-gradient shadow d-flex align-items-center justify-content-center p-4",
          "colorIcon": "fa fa-check text-secondary"
        },
        {
          "titulo": "Competencia en el mercado",
          "total": "120",
          "colorFond": "bg-success shadow d-flex align-items-center justify-content-center p-4",
          "colorIcon": "fa fa-award text-success"
        }
    ],
    "persons": [
        {
          "FullName": "Esteven Guardado Atencio",
          "Designation": "Desarrollador de Software",
          "Img": "/img/team-1.jpg",
          "SocialNetworks": {
            "urlFacebook": "#",
            "urlInstagram": "#",
            "urlLinkedIn": "#"
          }
        },
        {
          "FullName": "Keilor Arauz",
          "Designation": "Administrador General",
          "Img": "/img/team-2.jpg",
          "SocialNetworks": {
            "urlFacebook": "https://www.google.com/search?rlz=1C1ONGR_esCR1016CR1016&q=concatenate+%7B%22img/%22%7D+persons.img&sa=X&ved=2ahUKEwicrur78qn-AhUtg4QIHSsSD10Q7xYoAHoECB4QAQ&biw=1366&bih=649&dpr=1",
            "urlInstagram": "#",
            "urlLinkedIn": "#"
          }
        },
        {
          "FullName": "Ever Vega",
          "Designation": "Scrum Master",
          "Img": "/img/team-3.jpg",
          "SocialNetworks": {
            "urlFacebook": "#",
            "urlInstagram": "#",
            "urlLinkedIn": "#"
          }
        }
    ],
    "Chooses": [
        {
          "icono": "fa fa-cubes text-white",
          "titulo": "Mejor en el mercado"
        },
        {
          "icono": "fa fa-award text-white",
          "titulo": "Ganador de premios"
        },
        {
          "icono": "fa fa-users-cog text-white",
          "titulo": "Personal especializado"
        },
        {
          "icono": "fa fa-phone-alt text-white",
          "titulo": "Soporte 24/7"
        }
      ]
}